LICENSE.txt
MANIFEST.in
README.md
setup.cfg
setup.py
es/__init__.py
es/baseapi.py
es/basesqlalchemy.py
es/const.py
es/exceptions.py
es/elastic/__init__.py
es/elastic/api.py
es/elastic/sqlalchemy.py
es/opendistro/__init__.py
es/opendistro/api.py
es/opendistro/sqlalchemy.py
es/tests/__init__.py
es/tests/test_0_fixtures.py
es/tests/test_dbapi.py
es/tests/test_sqlalchemy.py
es/tests/fixtures/__init__.py
es/tests/fixtures/data1.json
es/tests/fixtures/data1_mappings.json
es/tests/fixtures/fixtures.py
es/tests/fixtures/flights.json
pupu_elasticsearch_dbapi.egg-info/PKG-INFO
pupu_elasticsearch_dbapi.egg-info/SOURCES.txt
pupu_elasticsearch_dbapi.egg-info/dependency_links.txt
pupu_elasticsearch_dbapi.egg-info/entry_points.txt
pupu_elasticsearch_dbapi.egg-info/not-zip-safe
pupu_elasticsearch_dbapi.egg-info/requires.txt
pupu_elasticsearch_dbapi.egg-info/top_level.txt