Metadata-Version: 2.1
Name: pupu-elasticsearch-dbapi
Version: 0.2.0
Summary: A DBAPI and SQLAlchemy dialect for Elasticsearch
Home-page: http://preset.io
Author: Preset Inc.
Author-email: daniel@preset.io
License: Apache License, Version 2.0
Download-URL: https://github.com/preset-io/elasticsearch-dbapi/releases/tag/0.2.0
Platform: UNKNOWN
Classifier: Programming Language :: Python :: 3.6
Classifier: Programming Language :: Python :: 3.7
Classifier: Programming Language :: Python :: 3.8
Classifier: Programming Language :: Python :: 3.9
Provides-Extra: opendistro
